evdev/__init__.py
evdev/_ecodes.cpython-39-x86_64-linux-gnu.so
evdev/_input.cpython-39-x86_64-linux-gnu.so
evdev/_uinput.cpython-39-x86_64-linux-gnu.so
evdev/device.py
evdev/ecodes.py
evdev/ecodes_runtime.py
evdev/eventio.py
evdev/eventio_async.py
evdev/events.py
evdev/evtest.py
evdev/ff.py
evdev/genecodes_c.py
evdev/genecodes_py.py
evdev/input.c
evdev/py.typed
evdev/uinput.c
evdev/uinput.py
evdev/util.py
evdev_binary-1.9.2.dist-info/METADATA
evdev_binary-1.9.2.dist-info/WHEEL
evdev_binary-1.9.2.dist-info/top_level.txt
evdev_binary-1.9.2.dist-info/RECORD
evdev_binary-1.9.2.dist-info/licenses/LICENSE
