Metadata-Version: 2.1
Name: evdev-binary
Version: 1.9.2
Summary: Bindings to the Linux input handling subsystem
Author-email: Georgi Valkov <georgi.t.valkov@gmail.com>
Maintainer-email: Tobi <proxima@sezanzeb.de>
License: Copyright (c) 2012-2025 Georgi Valkov. All rights reserved.
Project-URL: Homepage, https://github.com/gvalkov/python-evdev
Keywords: evdev,input,uinput
Classifier: Development Status :: 5 - Production/Stable
Classifier: Programming Language :: Python :: 3
Classifier: Operating System :: POSIX :: Linux
Classifier: Intended Audience :: Developers
Classifier: Topic :: Software Development :: Libraries
Classifier: License :: OSI Approved :: BSD License
Classifier: Programming Language :: Python :: Implementation :: CPython
Requires-Python: >=3.8
License-File: LICENSE
